{
  "version": "7",
  "dialect": "postgresql",
  "entries": [
    {
      "idx": 0,
      "version": "7",
      "when": 1779744655156,
      "tag": "0000_fat_barracuda",
      "breakpoints": true
    },
    {
      "idx": 1,
      "version": "7",
      "when": 1780045300684,
      "tag": "0001_closed_jazinda",
      "breakpoints": true
    },
    {
      "idx": 2,
      "version": "7",
      "when": 1780084547858,
      "tag": "0002_stiff_wendigo",
      "breakpoints": true
    },
    {
      "idx": 3,
      "version": "7",
      "when": 1780090000000,
      "tag": "0003_categories",
      "breakpoints": true
    }
  ]
}